rho_store/__init__.py
rho_store/adapters/__init__.py
rho_store/adapters/data_transport/__init__.py
rho_store/adapters/data_transport/rest_adapter.py
rho_store/adapters/data_transport/tests/__init__.py
rho_store/adapters/data_transport/tests/test_data_transport_rest_adapter.py
rho_store/adapters/rho_api/__init__.py
rho_store/adapters/rho_api/graphql_adapter.py
rho_store/adapters/rho_api/tests/__init__.py
rho_store/adapters/rho_api/tests/test_graphql_adapter_signed_url.py
rho_store/adapters/rho_api/types/__init__.py
rho_store/adapters/rho_api/utils.py
rho_store/adapters/upload_file/__init__.py
rho_store/adapters/upload_file/http_adapter.py
rho_store/adapters/upload_file/temp/__init__.py
rho_store/adapters/uptime_check/__init__.py
rho_store/adapters/uptime_check/uptime_check.py
rho_store/client.py
rho_store/config.py
rho_store/data/__init__.py
rho_store/data/spear_holdings.csv
rho_store/exceptions.py
rho_store/file_utils.py
rho_store/ports/__init__.py
rho_store/ports/data_transport_port.py
rho_store/table.py
rho_store/types/__init__.py
rho_store/types/query_options.py
rho_store/types/query_result.py
rho_store/types/store_df_command.py
rho_store/types/table_data_result.py
rho_store/types/upload_strategy.py
rho_store/utils.py
rho_store/validators.py
rho_store-0.1.52.dist-info/METADATA
rho_store-0.1.52.dist-info/WHEEL
rho_store-0.1.52.dist-info/RECORD
