Metadata-Version: 2.1
Name: rho-store
Version: 0.1.52
Summary: 
Author: Björn Ström
Author-email: bjornstrom90@gmail.com
Requires-Python: >=3.10,<3.13
Classifier: Programming Language :: Python :: 3
Classifier: Programming Language :: Python :: 3.10
Classifier: Programming Language :: Python :: 3.11
Classifier: Programming Language :: Python :: 3.12
Requires-Dist: cachetools (>=5.0.0,<6.0.0)
Requires-Dist: orjson (>=3.9.10,<4.0.0)
Requires-Dist: pandas (>=2.0.0,<3.0.0)
Requires-Dist: pyarrow (>=18.1.0,<19.0.0)
Requires-Dist: python-dotenv (>=1.0.0,<2.0.0)
Requires-Dist: requests (>=2.28.1,<3.0.0)
Requires-Dist: setuptools (>=69.1.0,<70.0.0)
